wagtail_bakery-0.2.0.dist-info/DESCRIPTION.rst
wagtail_bakery-0.2.0.dist-info/METADATA
wagtail_bakery-0.2.0.dist-info/RECORD
wagtail_bakery-0.2.0.dist-info/WHEEL
wagtail_bakery-0.2.0.dist-info/metadata.json
wagtail_bakery-0.2.0.dist-info/top_level.txt
wagtailbakery/__init__.py
wagtailbakery/api_views.py
wagtailbakery/apps.py
wagtailbakery/models.py
wagtailbakery/signal_handlers.py
wagtailbakery/views.py
wagtailbakery/templates/wagtailbakery/redirect.html
