Metadata-Version: 2.0
Name: wagtail-bakery
Version: 0.2.0
Summary: A set of helpers for baking your Django Wagtail site out as flat files.
Home-page: UNKNOWN
Author: Rob Moorman
Author-email: rob@moori.nl
License: UNKNOWN
Platform: UNKNOWN
Classifier: Environment :: Web Environment
Classifier: Framework :: Django
Classifier: Operating System :: Unix
Classifier: Programming Language :: Python :: 2
Classifier: Programming Language :: Python :: 2.7
Classifier: Programming Language :: Python :: 3
Classifier: Programming Language :: Python :: 3.5
Classifier: Programming Language :: Python :: 3.6
Requires-Dist: django-bakery (==0.12.3)
Requires-Dist: six (>=1.10.0)
Requires-Dist: wagtail (>=1.6)
Provides-Extra: test
Requires-Dist: factory-boy (==2.8.1); extra == 'test'
Requires-Dist: flake8 (==3.2.1); extra == 'test'
Requires-Dist: isort (==4.2.5); extra == 'test'
Requires-Dist: pytest (==3.0.5); extra == 'test'
Requires-Dist: pytest-cov (==2.4.0); extra == 'test'
Requires-Dist: pytest-django (==3.1.2); extra == 'test'
